gr_nlp_toolkit/__init__.py
gr_nlp_toolkit/configs/__init__.py
gr_nlp_toolkit/configs/dictionary_tables.py
gr_nlp_toolkit/configs/dp_labels.py
gr_nlp_toolkit/configs/ner_labels.py
gr_nlp_toolkit/configs/pos_labels.py
gr_nlp_toolkit/data/__init__.py
gr_nlp_toolkit/data/downloader.py
gr_nlp_toolkit/data/downloader_gdrive.py
gr_nlp_toolkit/data/downloader_stub.py
gr_nlp_toolkit/data/processor_cache.py
gr_nlp_toolkit/data/util.py
gr_nlp_toolkit/domain/__init__.py
gr_nlp_toolkit/domain/dataset.py
gr_nlp_toolkit/domain/document.py
gr_nlp_toolkit/domain/textVectorizer.py
gr_nlp_toolkit/domain/token.py
gr_nlp_toolkit/models/__init__.py
gr_nlp_toolkit/models/dp_model.py
gr_nlp_toolkit/models/g2g_RBNLM_model.py
gr_nlp_toolkit/models/g2g_transformer_model.py
gr_nlp_toolkit/models/ner_model.py
gr_nlp_toolkit/models/pos_model.py
gr_nlp_toolkit/models/util.py
gr_nlp_toolkit/pipeline/__init__.py
gr_nlp_toolkit/pipeline/pipeline.py
gr_nlp_toolkit/processors/__init__.py
gr_nlp_toolkit/processors/abstract_processor.py
gr_nlp_toolkit/processors/dp.py
gr_nlp_toolkit/processors/g2g.py
gr_nlp_toolkit/processors/ner.py
gr_nlp_toolkit/processors/pos.py
gr_nlp_toolkit/processors/tokenizer.py
tests/__init__.py
tests/domain/__init__.py
tests/domain/test_token.py
tests/test_data/__init__.py
tests/test_data/test_processor_cache.py
tests/test_pipeline/__init__.py
tests/test_pipeline/test_pipeline.py
tests/test_processors/__init__.py
tests/test_processors/test_dp.py
tests/test_processors/test_g2g.py
tests/test_processors/test_ner.py
tests/test_processors/test_pos.py
tests/test_processors/test_tokenizer.py
gr_nlp_toolkit-0.2.1.dist-info/LICENSE
gr_nlp_toolkit-0.2.1.dist-info/METADATA
gr_nlp_toolkit-0.2.1.dist-info/WHEEL
gr_nlp_toolkit-0.2.1.dist-info/top_level.txt
gr_nlp_toolkit-0.2.1.dist-info/RECORD
