Metadata-Version: 2.1
Name: gr-nlp-toolkit
Version: 0.2.1
Summary: The state-of-the-art NLP toolkit for (modern) Greek
Home-page: https://github.com/nlpaueb/gr-nlp-toolkit
Author: nlpaueb
Author-email: p3170148@aueb.gr, p3170039@aueb.gr, spirosbarbakos@gmail.com,  eleftheriosloukas@aueb.gr, ipavlopoulos@aueb.gr
Classifier: Programming Language :: Python :: 3
Classifier: License :: OSI Approved :: Apache Software License
Classifier: Operating System :: OS Independent
Classifier: Topic :: Text Processing :: Linguistic
Classifier: Natural Language :: Greek
Requires-Python: >=3.9
License-File: LICENSE
Requires-Dist: torch>=2.1.2
Requires-Dist: transformers>=4.11.1
Requires-Dist: huggingface-hub>=0.23.5
